{
  "DATA_PROJECT_ID":"qlts-nonprod-data-tools",
  "DATA_PROJECT_REGION":"us-central1",
  "DATA_DATAFUSION_INSTANCE_NAME":"qlts-data-fusion-dev",
  "DATA_DATAFUSION_TEMPORARY_BUCKET_NAME":"gcs-qlts-dev-mx-au-bro-verificaciones",
  "DATA_DATAPROC_CLUSTER_NAME":"verificaciones-dataproc",
  "DATA_DATAPROC_PROFILE_NAME":"USER:verificaciones-dataproc",

  "VERIFICACIONES_PROJECT_ID":"qlts-dev-mx-au-bro-verificacio",
  "VERIFICACIONES_PROJECT_REGION":"us-central1",
  "VERIFICACIONES_LAN_DATASET_NAME":"LAN_VERIFICACIONES",
  "VERIFICACIONES_RTL_DATASET_NAME":"RTL_VERIFICACIONES",
  "VERIFICACIONES_STG_DATASET_NAME":"STG_VERIFICACIONES",
  "VERIFICACIONES_DM_DATASET_NAME":"DM_VERIFICACIONES",
  "VERIFICACIONES_SEED_DATASET_NAME":"SEED_VERIFICACIONES",

  "APP_ORACLE_HOST":"qualitas-clm.cgriqmyweq5c.us-east-2.rds.amazonaws.com",
  "APP_ORACLE_SERVICE_NAME":"ORCL",
  "APP_ORACLE_USER":"ADMIN",
  "APP_ORACLE_PASSWORD":"FqzJ3n3Kvwcftakshcmi"   
}

